Metadata-Version: 2.1
Name: fakenamegenerator
Version: 0.1.0
Summary: Very mimimalistic unofficial python API for fakenamegenerator.com
Author: Vetochka
Author-email: vetochka@ulis.family
Classifier: Programming Language :: Python :: 3
Classifier: License :: OSI Approved :: MIT License
Classifier: Operating System :: OS Independent
Requires-Python: >=3.6
License-File: LICENSE
